socid_extractor/__init__.py
socid_extractor/__main__.py
socid_extractor/activation.py
socid_extractor/cli.py
socid_extractor/main.py
socid_extractor/postprocessor.py
socid_extractor/schemes.py
socid_extractor/utils.py
tests/__init__.py
tests/test_e2e.py
socid_extractor-0.0.26.dist-info/LICENSE
socid_extractor-0.0.26.dist-info/METADATA
socid_extractor-0.0.26.dist-info/WHEEL
socid_extractor-0.0.26.dist-info/entry_points.txt
socid_extractor-0.0.26.dist-info/top_level.txt
socid_extractor-0.0.26.dist-info/RECORD
