Metadata-Version: 2.1
Name: socid-extractor
Version: 0.0.26
Summary: Extract accounts' identifiers from personal pages on various platforms
Home-page: https://github.com/soxoj/socid-extractor
Author: Soxoj
Author-email: soxoj@protonmail.com
License: GPL-3.0
License-File: LICENSE
